LICENSE
MANIFEST.in
README.rst
dephp.py
setup.py
dephp.egg-info/PKG-INFO
dephp.egg-info/SOURCES.txt
dephp.egg-info/dependency_links.txt
dephp.egg-info/entry_points.txt
dephp.egg-info/requires.txt
dephp.egg-info/top_level.txt