Metadata-Version: 1.1
Name: dephp
Version: 0.4.0
Summary: Unofficial CLI application that decodes files through unphp.net web service
Home-page: http://github.com/mtorromeo/dephp
Author: Massimiliano Torromeo
Author-email: massimiliano.torromeo@gmail.com
License: BSD License
Download-URL: http://github.com/mtorromeo/dephp/tarball/v0.4.0
Platform: UNKNOWN
Classifier: Programming Language :: Python
Classifier: Programming Language :: Python :: 2
Classifier: Programming Language :: Python :: 3
Classifier: Development Status :: 5 - Production/Stable
Classifier: License :: OSI Approved :: BSD License
Classifier: Operating System :: MacOS :: MacOS X
Classifier: Operating System :: POSIX :: Linux
Classifier: Operating System :: POSIX :: BSD
Classifier: Natural Language :: English
